load_for_database/__init__.py
load_for_database/load_data.py
load_for_database-0.3.0.dist-info/LICENSE
load_for_database-0.3.0.dist-info/METADATA
load_for_database-0.3.0.dist-info/WHEEL
load_for_database-0.3.0.dist-info/top_level.txt
load_for_database-0.3.0.dist-info/RECORD
