Metadata-Version: 2.1
Name: load-for-database
Version: 0.3.0
Summary: Function to load data from XLSX files to a SQL Server database
Home-page: https://github.com/Bononi48/load_for_database.git
Author: Lucas Bononi
Author-email: contatobononi@gmail.com
License: UNKNOWN
Platform: UNKNOWN
Classifier: Programming Language :: Python :: 3
Classifier: License :: OSI Approved :: MIT License
Classifier: Operating System :: OS Independent
Requires-Python: >=3.6
License-File: LICENSE
Requires-Dist: pandas
Requires-Dist: sqlalchemy
Requires-Dist: pyodbc
Requires-Dist: openpyxl
